tf_transformers/__init__.py
tf_transformers/activations/__init__.py
tf_transformers/activations/gelu.py
tf_transformers/activations/swish.py
tf_transformers/activations/utils.py
tf_transformers/callbacks/__init__.py
tf_transformers/callbacks/metric_callback_list.py
tf_transformers/callbacks/metrics/__init__.py
tf_transformers/callbacks/metrics/callbacks.py
tf_transformers/callbacks/metrics/pearson_spearman_callback.py
tf_transformers/callbacks/metrics/sklearn_callbacks.py
tf_transformers/callbacks/metrics/text_generation_callbacks.py
tf_transformers/core/__init__.py
tf_transformers/core/chainer.py
tf_transformers/core/distribute_utils.py
tf_transformers/core/keras_utils.py
tf_transformers/core/legacy_compile.py
tf_transformers/core/legacy_layer.py
tf_transformers/core/legacy_model.py
tf_transformers/core/legacy_module.py
tf_transformers/core/model_wrapper.py
tf_transformers/core/performance_utils.py
tf_transformers/core/read_from_hub.py
tf_transformers/core/trainer.py
tf_transformers/core/transformer_config.py
tf_transformers/data/__init__.py
tf_transformers/data/callbacks/__init__.py
tf_transformers/data/callbacks/mlm_callback.py
tf_transformers/data/ner_utils_sp.py
tf_transformers/data/processors/__init__.py
tf_transformers/data/processors/mlm.py
tf_transformers/data/processors/mlm_ttext.py
tf_transformers/data/squad_utils_sp.py
tf_transformers/data/tfprocessor_utils.py
tf_transformers/data/tfrecord_utils.py
tf_transformers/data/utils.py
tf_transformers/layers/__init__.py
tf_transformers/layers/attention/__init__.py
tf_transformers/layers/attention/bart_attention.py
tf_transformers/layers/attention/bert_attention.py
tf_transformers/layers/attention/bigbird_attention.py
tf_transformers/layers/attention/clip_attention.py
tf_transformers/layers/attention/gpt2_attention.py
tf_transformers/layers/attention/t5_attention.py
tf_transformers/layers/bias_layer.py
tf_transformers/layers/dense_einsum.py
tf_transformers/layers/image_embeddings.py
tf_transformers-2.0.0.dist-info/LICENSE
tf_transformers-2.0.0.dist-info/WHEEL
tf_transformers-2.0.0.dist-info/METADATA
tf_transformers-2.0.0.dist-info/RECORD
