Metadata-Version: 2.1
Name: tf-transformers
Version: 2.0.0
Summary: NLP with Transformer based models on Tensorflow 2.0
License: MIT
Keywords: tensorflow,transformers,nlp,keras,bert,deep learning
Author: Sarath R Nair
Author-email: s4sarath@gmail.com
Maintainer: Sarath R Nair
Maintainer-email: s4sarath@gmail.com
Requires-Python: >=3.7,<4.0
Classifier: License :: OSI Approved :: MIT License
Classifier: Programming Language :: Python :: 3
Classifier: Programming Language :: Python :: 3.10
Classifier: Programming Language :: Python :: 3.7
Classifier: Programming Language :: Python :: 3.8
Classifier: Programming Language :: Python :: 3.9
Requires-Dist: absl-py (>=1.0.0,<2.0.0)
Requires-Dist: sentencepiece (>=0.1.96,<0.2.0)
Requires-Dist: tqdm (>=4.62.3,<5.0.0)
Requires-Dist: transformers (>=4.15.0,<5.0.0)
